flask_mongobit/__init__.py
flask_mongobit-0.3.1.dist-info/METADATA
flask_mongobit-0.3.1.dist-info/WHEEL
flask_mongobit-0.3.1.dist-info/top_level.txt
flask_mongobit-0.3.1.dist-info/RECORD
